{
  "schema": "fc26-ai-character-studio/full-career-import-2.0",
  "generated_utc": "2026-07-23T17:42:39Z",
  "project_id": "b05e39e56dc14fa5b586c6900b547f9d",
  "project_name": "Nouveau personnage",
  "score": 12.467,
  "previous_score": 12.467,
  "source_save": "CmPlr20260325001839527",
  "source_sha256": "1c0a088e72d02234797865dfc87edde2fd3621f6d4a3efd71bdc1fee7da762e7",
  "source_untouched": true,
  "backup_relative": "workspace/imports/backups/CmPlr20260325001839527.20260723194239.backup",
  "output_save": "CmPlr20260723194239500",
  "output_sha256": "296785afd924180f896682e1dee422104c0d905ef40bc58652d6bf198de384a8",
  "file_size_unchanged": true,
  "axes_requested": 618,
  "axes_readback_ok": 618,
  "changed_byte_count": 578,
  "all_changes_inside_cranium_fields": true,
  "appearance": {},
  "appearance_status": "FC26 materials preserved from source save; morph import completed",
  "safety": {
    "fc26_was_closed": true,
    "source_save_modified": false,
    "separate_copy_created": true,
    "game_files_modified": false,
    "anti_cheat_touched": false,
    "crc_bytes_modified": false
  }
}